solders-0.27.1.dist-info/METADATA
solders-0.27.1.dist-info/WHEEL
solders-0.27.1.dist-info/license_files/LICENSE
solders/epoch_info.py
solders/sysvar.py
solders/transaction_status.py
solders/address_lookup_table_account.py
solders/epoch_schedule.py
solders/signature.py
solders/solders.pyi
solders/keypair.py
solders/commitment_config.py
solders/instruction.py
solders/clock.py
solders/null_signer.py
solders/epoch_rewards.py
solders/rpc/responses.py
solders/rpc/requests.py
solders/rpc/filter.py
solders/rpc/config.py
solders/rpc/__init__.py
solders/rpc/errors.py
solders/compute_budget.py
solders/transaction.py
solders/stake_history.py
solders/message.py
solders/hash.py
solders/account.py
solders/py.typed
solders/token/associated.py
solders/token/state.py
solders/token/__init__.py
solders/litesvm.py
solders/presigner.py
solders/rent.py
solders/pubkey.py
solders/account_decoder.py
solders/system_program.py
solders/transaction_metadata.py
solders/__init__.py
solders/slot_history.py
solders/errors.py
solders/solders.abi3.so
solders-0.27.1.dist-info/RECORD
