Metadata-Version: 2.1
Name: solders
Version: 0.27.1
Classifier: Programming Language :: Rust
Classifier: Programming Language :: Python :: Implementation :: CPython
Classifier: Programming Language :: Python :: Implementation :: PyPy
Requires-Dist: typing-extensions >=4.2.0
Requires-Dist: jsonalias ==0.1.1
License-File: LICENSE
Summary: Python bindings for Solana Rust tools
Author-email: kevinheavey <kevinheavey123@gmail.com>
License: MIT
Requires-Python: >=3.8,<4.0
Project-URL: homepage, https://github.com/kevinheavey/solders
Project-URL: documentation, https://kevinheavey.github.io/solders/
Project-URL: repository, https://github.com/kevinheavey/solders
Project-URL: changelog, https://github.com/kevinheavey/solders/blob/main/CHANGELOG.md
